MANIFEST.in
setup.cfg
setup.py
versioneer.py
GameOfThrones/__init__.py
GameOfThrones/_version.py
GameOfThrones/data/Season1.dev.lst
GameOfThrones/data/Season1.trn.lst
GameOfThrones/data/Season1.tst.lst
GameOfThrones/data/Season1Test.tst.lst
GameOfThrones/data/audio/GameOfThrones.Season01.Episode01.txt
GameOfThrones/data/audio/GameOfThrones.Season01.Episode02.txt
GameOfThrones/data/audio/GameOfThrones.Season01.Episode03.txt
GameOfThrones/data/audio/GameOfThrones.Season01.Episode04.txt
GameOfThrones/data/audio/GameOfThrones.Season01.Episode05.txt
GameOfThrones/data/audio/GameOfThrones.Season01.Episode06.txt
GameOfThrones/data/audio/GameOfThrones.Season01.Episode07.txt
GameOfThrones/data/audio/GameOfThrones.Season01.Episode08.txt
GameOfThrones/data/audio/GameOfThrones.Season01.Episode09.txt
GameOfThrones/data/audio/GameOfThrones.Season01.Episode10.txt
pyannote.db.gameofthrones.egg-info/PKG-INFO
pyannote.db.gameofthrones.egg-info/SOURCES.txt
pyannote.db.gameofthrones.egg-info/dependency_links.txt
pyannote.db.gameofthrones.egg-info/entry_points.txt
pyannote.db.gameofthrones.egg-info/requires.txt
pyannote.db.gameofthrones.egg-info/top_level.txt